<!DOCTYPE node PUBLIC "-//freedesktop//DTD D-BUS Object Introspection 1.0//EN"
 "http://www.freedesktop.org/standards/dbus/1.0/introspect.dtd">

<!--
/**
 * Nemo Password Manager: D-Bus Service for changing and generating passwords
 * Copyright (C) 2013 Jolla Ltd.
 * Contact: Thomas Perl <thomas.perl@jollamobile.com>
 *
 * This program is free software; you can redistribute it and/or
 * modify it under the terms of the GNU General Public License
 * as published by the Free Software Foundation; either version 2
 * of the License, or (at your option) any later version.
 *
 * This program is distributed in the hope that it will be useful,
 * but WITHOUT ANY WARRANTY; without even the implied warranty of
 * MERCHANTABILITY or FITNESS FOR A PARTICULAR PURPOSE.  See the
 * GNU General Public License for more details.
 *
 * You should have received a copy of the GNU General Public License
 * along with this program; if not, write to the Free Software
 * Foundation, Inc., 51 Franklin Street, Fifth Floor, Boston, MA  02110-1301, USA.
 **/
-->

<node name="/org/nemo/passwordmanager">
  <interface name="org.nemo.passwordmanager">
    <method name="setPassword">
      <arg direction="in" type="s" name="password"/>
    </method>
    <method name="generatePassword">
    </method>
    <method name="getGeneratedPassword">
      <arg direction="out" type="s" name="password"/>
    </method>
    <method name="quit">
    </method>

    <signal name="passwordChanged">
      <arg direction="out" type="s" name="password"/>
    </signal>
    <signal name="error">
      <arg direction="out" type="s" name="message"/>
    </signal>
  </interface>
</node>
